pyproject.toml
setup.cfg
setup.py
src/crosslab/soa_services/message/__init__.py
src/crosslab/soa_services/message/message_service.py
src/crosslab/soa_services/message/messages.py
src/crosslab/soa_services/message/py.typed
src/crosslab_soa_service_message.egg-info/PKG-INFO
src/crosslab_soa_service_message.egg-info/SOURCES.txt
src/crosslab_soa_service_message.egg-info/dependency_links.txt
src/crosslab_soa_service_message.egg-info/requires.txt
src/crosslab_soa_service_message.egg-info/top_level.txt
tests/test_standard.py